Utils/H5_TK.py
Utils/Mongo_conn.py
Utils/MyUtils.py
Utils/Rabbit_conn.py
Utils/Redis_conn.py
Utils/__init__.py
Utils/monitor_rabbit.py
Utils/my_middleware.py
Utils/proxy.py
zhanlan2-0.2.6.dist-info/LICENSE
zhanlan2-0.2.6.dist-info/METADATA
zhanlan2-0.2.6.dist-info/WHEEL
zhanlan2-0.2.6.dist-info/top_level.txt
zhanlan2-0.2.6.dist-info/RECORD
